minsprojectr/init.py
minsprojectr/operations.py
minsprojectr-0.0.3.dist-info/LICENSE
minsprojectr-0.0.3.dist-info/METADATA
minsprojectr-0.0.3.dist-info/WHEEL
minsprojectr-0.0.3.dist-info/top_level.txt
minsprojectr-0.0.3.dist-info/RECORD
