Metadata-Version: 2.1
Name: minsprojectr
Version: 0.0.3
Summary: A small package for basic mathematical operations
Author-email: Sai <sai275stw@gamil.com>
Classifier: Programming Language :: Python :: 3
Classifier: License :: OSI Approved :: MIT License
Classifier: Operating System :: OS Independent
Requires-Python: >=3.8
License-File: LICENSE
